{
  "id": "zygisksu",
  "timestamp": 1750569218.0,
  "versions": [
    {
      "timestamp": 1752237202.0,
      "version": "v1.0.0 (390-bc1b757-release)",
      "versionCode": 390,
      "zipUrl": "https://mystster.github.io/module-repo/modules/zygisksu/v1.0.0_390-bc1b757-release.zip",
      "changelog": "",
      "size": 441000
    },
    {
      "timestamp": 1752363117.0,
      "version": "v1.0.0 (392-407c81b-release)",
      "versionCode": 392,
      "zipUrl": "https://mystster.github.io/module-repo/modules/zygisksu/v1.0.0_392-407c81b-release.zip",
      "changelog": "",
      "size": 440545
    }
  ]
}